odoo/addons/github_connector_oca/README.rst
odoo/addons/github_connector_oca/__init__.py
odoo/addons/github_connector_oca/__manifest__.py
odoo/addons/github_connector_oca/models/__init__.py
odoo/addons/github_connector_oca/models/odoo_module_version.py
odoo/addons/github_connector_oca/readme/CONTRIBUTORS.rst
odoo/addons/github_connector_oca/readme/DESCRIPTION.rst
odoo/addons/github_connector_oca/readme/USAGE.rst
odoo/addons/github_connector_oca/static/description/icon.png
odoo/addons/github_connector_oca/static/description/index.html
odoo/addons/github_connector_oca/views/odoo_module_version.xml
odoo11_addon_github_connector_oca-11.0.1.0.0.99.dev5.dist-info/METADATA
odoo11_addon_github_connector_oca-11.0.1.0.0.99.dev5.dist-info/WHEEL
odoo11_addon_github_connector_oca-11.0.1.0.0.99.dev5.dist-info/top_level.txt
odoo11_addon_github_connector_oca-11.0.1.0.0.99.dev5.dist-info/RECORD
