Metadata-Version: 2.1
Name: odoo11-addon-github-connector-oca
Version: 11.0.1.0.0.99.dev5
Summary: Add OCA specific information to Odoo modules
Home-page: https://github.com/OCA/interface-github
Author: Odoo Community Association (OCA), Road-Support
Author-email: support@odoo-community.org
License: AGPL-3
Platform: UNKNOWN
Classifier: Programming Language :: Python
Classifier: Framework :: Odoo
Classifier: Framework :: Odoo :: 11.0
Classifier: License :: OSI Approved :: GNU Affero General Public License v3
Requires-Python: >=2.7, !=3.0.*, !=3.1.*, !=3.2.*, !=3.3.*, !=3.4.*
Requires-Dist: odoo11-addon-github-connector-odoo
Requires-Dist: odoo <11.1dev,>=11.0a
